[
    {
        "id": "1",
        "name": "Bessie",
        "birthday": "2015-01-01",
        "color": "black",
        "breed": "Holstein",
        "mother-id": null,
        "vaccinations": [
            {
                "id": "1",
                "name": "Bovine Viral Diarrhea",
                "date": "2018-01-01"
            },
            {
                "id": "2",
                "name": "Bovine Respiratory Disease",
                "date": "2018-04-01"
            },
            {
                "id": "3",
                "name": "Bovine Leukemia",
                "date": "2018-09-01"
            }
        ]
    },
    {
        "id": "2",
        "name": "Moo",
        "birthday": "2015-03-01",
        "color": "white",
        "breed": "Holstein",
        "mother-id": null,
        "vaccinations": [
            {
                "id": "1",
                "name": "Bovine Viral Diarrhea",
                "date": "2018-02-01"
            }
        ]
    },
    {
        "id": "3",
        "name": "Moooooo",
        "birthday": "2022-11-01",
        "color": "black",
        "breed": "Holstein",
        "mother-id": "1"
    },
    {
        "id": "4",
        "name": "Rari",
        "birthday": "2022-06-02",
        "color": "spotted",
        "breed": "Holstein",
        "mother-id": "3",
        "vaccinations": [
            {
                "id": 1,
                "name": "Bovine Tuberculosis",
                "date": "2022-11-26"
            }
        ]
    },
    {
        "id": "5",
        "name": "Rari",
        "birthday": "2022-11-04",
        "color": "brown",
        "breed": "Holstein",
        "mother-id": null
    },
    {
        "id": "6",
        "name": "Moooooo",
        "birthday": "2011-06-22",
        "color": "brown",
        "breed": "Holstein",
        "mother-id": null
    },
    {
        "id": "7",
        "name": "Hmousa",
        "birthday": "2022-11-03",
        "color": "spotted",
        "breed": "Jersey",
        "mother-id": null
    },
    {
        "id": "8",
        "name": "i'm a COW ?",
        "birthday": "2008-07-09",
        "color": "black",
        "breed": "Guernsey",
        "mother-id": null
    },
    {
        "id": "9",
        "name": "1339-test",
        "birthday": "2022-11-01",
        "color": "black",
        "breed": "Guernsey",
        "mother-id": "3"
    },
    {
        "id": "10",
        "name": "Doli",
        "birthday": "2022-11-26",
        "color": "brown",
        "breed": "Jersey",
        "mother-id": "3"
    }
]